earthscope_cli/__init__.py
earthscope_cli/common.py
earthscope_cli/debug.py
earthscope_cli/login.py
earthscope_cli/main.py
earthscope_cli/user.py
earthscope_cli/util.py
earthscope_cli/dropoff/render.py
earthscope_cli/dropoff/typer.py
earthscope_cli/dropoff/util.py
earthscope_cli-1.1.0.dist-info/licenses/LICENSE
earthscope_cli-1.1.0.dist-info/METADATA
earthscope_cli-1.1.0.dist-info/WHEEL
earthscope_cli-1.1.0.dist-info/entry_points.txt
earthscope_cli-1.1.0.dist-info/top_level.txt
earthscope_cli-1.1.0.dist-info/RECORD
