Metadata-Version: 2.4
Name: earthscope-cli
Version: 1.1.0
Summary: A CLI for the EarthScope API
Author-email: EarthScope <data-help@earthscope.org>
License:                                  Apache License
Project-URL: Homepage, https://gitlab.com/earthscope/public/earthscope-cli
Classifier: License :: OSI Approved :: Apache Software License
Classifier: Programming Language :: Python
Classifier: Programming Language :: Python :: 3
Classifier: Operating System :: OS Independent
Requires-Python: >=3.9
License-File: LICENSE
Requires-Dist: typer-slim>=0.17.3
Requires-Dist: typer-di>=0.1.3
Requires-Dist: earthscope-sdk>=1.3.0
Requires-Dist: rich>=13.8.0
Provides-Extra: dev
Requires-Dist: black; extra == "dev"
Requires-Dist: bumpver; extra == "dev"
Requires-Dist: build; extra == "dev"
Requires-Dist: pre-commit; extra == "dev"
Requires-Dist: pytest; extra == "dev"
Requires-Dist: twine; extra == "dev"
Requires-Dist: pip-tools; extra == "dev"
Dynamic: license-file
